nidl/__init__.py
nidl/experiment.py
nidl/info.py
nidl/transforms.py
nidl/callbacks/__init__.py
nidl/callbacks/check_typing.py
nidl/callbacks/model_probing.py
nidl/callbacks/multitask_probing.py
nidl/datasets/__init__.py
nidl/datasets/base.py
nidl/datasets/openbhb.py
nidl/datasets/pandas_dataset.py
nidl/estimators/__init__.py
nidl/estimators/base.py
nidl/estimators/autoencoders/__init__.py
nidl/estimators/autoencoders/vae.py
nidl/estimators/linear/__init__.py
nidl/estimators/linear/logistic_regression.py
nidl/estimators/ssl/__init__.py
nidl/estimators/ssl/barlowtwins.py
nidl/estimators/ssl/simclr.py
nidl/estimators/ssl/yaware.py
nidl/estimators/ssl/utils/__init__.py
nidl/estimators/ssl/utils/projection_heads.py
nidl/losses/__init__.py
nidl/losses/barlowtwins.py
nidl/losses/beta_vae.py
nidl/losses/infonce.py
nidl/losses/yaware_infonce.py
nidl/metrics/__init__.py
nidl/metrics/_regression.py
nidl/metrics/classification.py
nidl/metrics/regression.py
nidl/utils/__init__.py
nidl/utils/bunch.py
nidl/utils/color.py
nidl/utils/validation.py
nidl/utils/weights.py
nidl/volume/__init__.py
nidl/volume/backbones/__init__.py
nidl/volume/backbones/alexnet3d.py
nidl/volume/backbones/densenet3d.py
nidl/volume/backbones/resnet3d.py
nidl/volume/transforms/__init__.py
nidl/volume/transforms/augmentation/__init__.py
nidl/volume/transforms/augmentation/intensity/__init__.py
nidl/volume/transforms/augmentation/intensity/random_blur.py
nidl/volume/transforms/augmentation/intensity/random_noise.py
nidl/volume/transforms/augmentation/spatial/__init__.py
nidl/volume/transforms/augmentation/spatial/random_erasing.py
nidl/volume/transforms/augmentation/spatial/random_flip.py
nidl/volume/transforms/augmentation/spatial/random_resized_crop.py
nidl/volume/transforms/augmentation/spatial/random_rotation.py
nidl/volume/transforms/preprocessing/__init__.py
nidl/volume/transforms/preprocessing/intensity/__init__.py
nidl/volume/transforms/preprocessing/intensity/rescale.py
nidl-0.0.1.dist-info/licenses/AUTHORS.rst
nidl-0.0.1.dist-info/licenses/LICENSE.rst
nidl-0.0.1.dist-info/METADATA
nidl-0.0.1.dist-info/WHEEL
nidl-0.0.1.dist-info/top_level.txt
nidl-0.0.1.dist-info/RECORD
