Metadata-Version: 2.4
Name: nidl
Version: 0.0.1
Author-email: Antoine Grigis <antoine.grigis@cea.fr>, Benoit Dufumier <benoit.dufumier@cea.fr>, Joël Chavas <joel.chavas@cea.fr>
License-Expression: CECILL-B
Project-URL: Source, https://github.com/neurospin-deppinsight/nidl
Project-URL: Tracker, https://github.com/neurospin-deppinsight/nidl/issues
Platform: Linux
Platform: OSX
Classifier: Development Status :: 1 - Planning
Classifier: Environment :: Console
Classifier: Operating System :: OS Independent
Classifier: Programming Language :: Python
Classifier: Topic :: Scientific/Engineering
Requires-Python: >=3.9
License-File: LICENSE.rst
License-File: AUTHORS.rst
Requires-Dist: torch<2.8.0,>=2.1.0
Requires-Dist: pytorch-lightning
Requires-Dist: torchvision
Requires-Dist: toml
Requires-Dist: python-typex
Requires-Dist: pandas
Requires-Dist: scikit-learn<=1.7.0
Requires-Dist: simpleitk
Requires-Dist: nibabel
Provides-Extra: plugins
Requires-Dist: surfify; extra == "plugins"
Provides-Extra: openbhb
Requires-Dist: huggingface_hub; extra == "openbhb"
Provides-Extra: doc
Requires-Dist: docutils>=0.17; extra == "doc"
Requires-Dist: furo>=2024.8.6; extra == "doc"
Requires-Dist: memory_profiler>=0.61.0; extra == "doc"
Requires-Dist: myst-parser>=3.0.1; extra == "doc"
Requires-Dist: numpydoc>=1.8.0; extra == "doc"
Requires-Dist: ruamel.yaml>=0.18.6; extra == "doc"
Requires-Dist: sphinx>=7.4.7; extra == "doc"
Requires-Dist: sphinx-copybutton>=0.5.2; extra == "doc"
Requires-Dist: sphinx-design>=0.6.1; extra == "doc"
Requires-Dist: sphinx-gallery>=0.18.0; extra == "doc"
Requires-Dist: sphinxcontrib-bibtex>=2.6.3; extra == "doc"
Requires-Dist: sphinxext-opengraph>=0.9.1; extra == "doc"
Requires-Dist: sphinxcontrib-mermaid>=1.0.0; extra == "doc"
Dynamic: license-file
